wsmf/__init__.py
wsmf/metamodels/data/__init__.py
wsmf/metamodels/data/dataset.py
wsmf/metamodels/data/landmarker_reconstruction.py
wsmf/metamodels/data/metric_loader.py
wsmf/metamodels/data/repeatable.py
wsmf/metamodels/networks/__init__.py
wsmf/metamodels/networks/d2v_metric.py
wsmf/metamodels/networks/d2v_reconstruction.py
wsmf/metamodels/train/__init__.py
wsmf/metamodels/train/interface.py
wsmf/metamodels/train/metric.py
wsmf/metamodels/train/reconstruction.py
wsmf/selectors/__init__.py
wsmf/selectors/baselines.py
wsmf/selectors/reconstruction_based.py
wsmf/selectors/representation_based.py
wsmf/selectors/selector.py
wsmf/selectors/utils.py
wsmf-0.0.2.dist-info/METADATA
wsmf-0.0.2.dist-info/WHEEL
wsmf-0.0.2.dist-info/top_level.txt
wsmf-0.0.2.dist-info/RECORD
